sngtolib/__init__.py
sngtolib/myfunctions.py
sngtolib/sngto.py
sngtolib-1.2.dist-info/LICENSE
sngtolib-1.2.dist-info/METADATA
sngtolib-1.2.dist-info/WHEEL
sngtolib-1.2.dist-info/top_level.txt
sngtolib-1.2.dist-info/RECORD
