Metadata-Version: 2.1
Name: sngtolib
Version: 1.2
Summary: Lib số nguyên tố và các hàm liên quan đến số nguyên tố trong Python 3
Home-page: UNKNOWN
Author: DavidBisky
License: Mozilla Public License Version 2.0
Platform: UNKNOWN
License-File: LICENSE
